{
    "Ano": "2015",
    "Campus": "CAMPUS CUIABÁ",
    "Curso": "MEDICINA - BACHARELADO",
    "Tipo de Ingresso": "INGRESSO POR PROCESSO SELETIVO ENEM (SISU)",
    "Período de ingresso": "20141",
    "Sexo": "Feminino",
    "Nascimento": "25/11/1995",
    "Nota": "739,68",
    "Integralização": "34.00",
    "Situação atual": "MATRICULADO NO PERÍODO",
    "Período": "20171",
    "Demanda": "L2 - Renda igual ou inferior 1,5 salário mínimo e estudande preto pardo ou indígena de esc. pública",
    "i": 17954
}