{
    "Ano": "2016",
    "Campus": "CAMPUS ARAGUAIA",
    "Curso": "LICENCIATURA EM QUÍMICA - CRÉDITO",
    "Tipo de Ingresso": "INGRESSO POR PROCESSO SELETIVO ENEM (SISU)",
    "Período de ingresso": "20161",
    "Sexo": "Feminino",
    "Nascimento": "21/03/1983",
    "Nota": "479,14",
    "Integralização": "9.00",
    "Situação atual": "AFASTAMENTO POR NAO MATRICULA",
    "Período": "20171",
    "Demanda": "L2 - Renda igual ou inferior 1,5 salário mínimo e estudante preto pardo ou indígena de esc. pública",
    "i": 2389
}