{
    "Ano": "2016",
    "Campus": "CAMPUS CUIABÁ",
    "Curso": "CIENCIAS CONTABEIS - SERIADO MATUTINO",
    "Tipo de Ingresso": "INGRESSO POR PROCESSO SELETIVO ENEM (SISU)",
    "Período de ingresso": "20161",
    "Sexo": "Masculino",
    "Nascimento": "12/08/1996",
    "Nota": "594,66",
    "Integralização": "24.00",
    "Situação atual": "MATRICULADO NO PERÍODO",
    "Período": "20171",
    "Demanda": "L1 - Renda igual ou inferior 1,5 salário mínimo e estudante de escola pública",
    "i": 40639
}