{
    "Ano": "2016",
    "Campus": "CAMPUS SINOP",
    "Curso": "ENGENHARIA AGRÍCOLA E AMBIENTAL  BACHARELADO",
    "Tipo de Ingresso": "INGRESSO POR PROCESSO SELETIVO ENEM (SISU)",
    "Período de ingresso": "20131",
    "Sexo": "Masculino",
    "Nascimento": "09/10/1992",
    "Nota": "593,46",
    "Integralização": "17.00",
    "Situação atual": "EXCLUSAO POR DESISTENCIA",
    "Período": "20162",
    "Demanda": "Acão Afirmativa - L4 Estudante Escolar Pública e autodeclarado raça",
    "i": 41313
}