{
    "Ano": "2016",
    "Campus": "CAMPUS SINOP",
    "Curso": "CIÊNCIAS NATURAIS E MATEMÁTICA: HAB. QUÍMICA",
    "Tipo de Ingresso": "INGRESSO POR PROCESSO SELETIVO ENEM (SISU)",
    "Período de ingresso": "20161",
    "Sexo": "Feminino",
    "Nascimento": "16/06/1986",
    "Nota": "411,30",
    "Integralização": "100.00",
    "Situação atual": "EXCLUSAO POR CONCLUSAO (FORMADO)",
    "Período": "20161",
    "Demanda": "L2 - Renda igual ou inferior 1,5 salário mínimo e estudante preto pardo ou indígena de esc. pública",
    "i": 5098
}